Workbook

Sheet Dashboard
C1: Cloudflare, Inc. — Edge Growth Console | Q1: ="● DBNR "&TEXT('Raw Data'!F22,"0%")&" exit "&"● Large-cust. mix "&TEXT('Raw Data'!F23,"0%")&" "&"● Op. margin "&TEXT('Calculated KPIs'!F8,"0.0%")&" "&"● RPO $"&TEXT('Raw Data'!F26/1000,"0.00")&"B "&TEXT('Calculated KPIs'!F28,"+0%;-0%")&" YoY" -> ● DBNR 120% exit ● Large-cust. mix 69% ● Op. margin -9.3% ● RPO $2.50B +48% YoY | AC1: FY25 EXIT RATE
C2: NYSE: NET · GAAP basis, $ in millions · FY2021-FY2025
A4: FY25 REVENUE | F4: GROSS MARGIN | K4: FREE CASH FLOW | P4: NET RETENTION | U4: LARGE CUSTOMERS | Z4: NET LOSS
A5: ='Raw Data'!F6 -> 2167.9 | F5: ='Calculated KPIs'!F7 -> 0.74514507 | K5: ='Raw Data'!F15 -> 281 | P5: ='Raw Data'!F22 -> 1.2 | U5: ='Raw Data'!F20 -> 4298 | Z5: ='Raw Data'!F13 -> -102.3
A8: ="▲ "&TEXT('Calculated KPIs'!F6,"0.0%")&" YoY growth" -> ▲ 29.8% YoY growth | F8: ="vs. "&TEXT('Calculated KPIs'!E7,"0.0%")&" in FY24" -> vs. 77.3% in FY24 | K8: =TEXT('Calculated KPIs'!F10,"0.00%")&" FCF margin" -> 12.96% FCF margin | P8: ="▼ from "&TEXT('Raw Data'!B22,"0%")&" in FY21" -> ▼ from 125% in FY21 | U8: ="▲ "&TEXT('Calculated KPIs'!F21,"0.0%")&" YoY · >$100K ARR" -> ▲ 22.9% YoY · >$100K ARR | Z8: ="Narrowed from "&TEXT('Raw Data'!B13,"$#,##0.0")&"M FY21" -> Narrowed from -$260.3M FY21
V31: 4-YEAR CAGR (FY2021 -> FY2025)
V32: Compounded annual growth
V33: Revenue CAGR | AB33: ='Calculated KPIs'!$B$39 -> 0.34808622
V36: Customer CAGR (FY23-25, 2yr) | AB36: ='Calculated KPIs'!$B$40 -> 0.32357246
V39: FCF CAGR (FY23-25, 2yr) | AB39: ='Calculated KPIs'!$B$41 -> 0.448648

Sheet README
B2: Cloudflare (NET) — V1 Financial & Operating Dataset, FY2021–FY2025
B4: This workbook contains the finalized V1 raw dataset (Tab 2) plus a derived KPI table (Tab 3), built for the Advanced Excel + Power BI showcase project discussed in chat.
B6: How to use this workbook
B7: • 'Raw Data' tab holds every sourced, hardcoded figure (blue font). These are inputs — do not overwrite with formulas.
B8: • 'Calculated KPIs' tab derives every ratio (black font) from the Raw Data tab via formulas — nothing here is hardcoded.
B9: • Cells shaded yellow in Raw Data are flagged assumptions or figures worth double-checking against the original 10-K/8-K if this feeds a graded deliverable.
B10: • 'n/a' means the company did not disclose this metric for that fiscal year in the sources reviewed — it was left blank rather than estimated.
B12: Data sources
B13: • Cloudflare, Inc. Q4/FY press releases (2021–2025), businesswire.com / cloudflare.com, and Q3/Q4 2025 earnings call transcripts (fool.com, SEC EDGAR).
B14: • StockAnalysis.com (data provider: S&P Global Market Intelligence / Fiscal.ai) used for standardized annual Income Statement, Cash Flow, Geographic Revenue, and KPI history where original press releases only report at the quarterly level.
B15: • SEC EDGAR 10-K filings (CIK 1477333) for segment/expense detail.
B17: Known limitations (be aware before presenting this as final)
... B21: • FY2025 Dollar-Based Net Retention and Large Customer Revenue % use the Q4 2025 exit rate as reported; full-year weighted-average figures are cited separately as 'FY2025 avg.' in Raw Data notes where disclosed.

Sheet Raw Data
A1: Cloudflare, Inc. (NET) — Raw Dataset, FY2021–FY2025
A2: All dollar figures in $ millions (GAAP) unless noted. Black = hardcoded source figure. Yellow fill = flagged assumption/derivation. Fiscal year ends Dec 31.
A4: Metric | B4: FY2021 | C4: FY2022 | D4: FY2023 | E4: FY2024 | F4: FY2025 | G4: Source / Note
A5: FINANCIAL
A6: 1. Revenue | B6: 656.4 | C6: 975.2 | D6: 1296.7 | E6: 1669.6 | F6: 2167.9 | G6: Source: Cloudflare Q4/FY press releases, 2021–2025 (cloudflare.com/press). Company-reported GAAP total revenue.
A7: 2. Cost of Revenue | B7: 147.1 | C7: 232.6 | D7: 307 | E7: 378.7 | F7: 552.5 | G7: Derived per plan: Cost of Revenue = Revenue − Gross Profit. Cross-checked against StockAnalysis.com standardized income statement (matches).
A8: 3. Gross Profit | B8: 509.3 | C8: 742.6 | D8: 989.7 | E8: 1290.9 | F8: 1615.4 | G8: Source: Cloudflare Q4/FY press releases 2021–2025 (GAAP gross profit).
A9: 4. SG&A (Sales & Mktg + G&A, combined) | B9: 447.2 | C9: 641.6 | D9: 817.1 | E9: 1009 | F9: 1303.6 | G9: Source: StockAnalysis.com standardized income statement (S&P Global Market Intelligence), GAAP basis. Cloudflare does report S&M and G&A as separate GAAP line items each quarter (e.g. Q2'22: S&M $103.9M, G&A $35.8M) — kept combined here only because a clean full-year GAAP split for all 5 years wasn't assembled in this session; splitting it is a quick pull from each year's 10-K if needed.
A10: 5. R&D | B10: 189.4 | C10: 298.3 | D10: 358.1 | E10: 421.4 | F10: 512.5 | G10: Source: Cloudflare 10-K filings / MacroTrends.net (GAAP R&D expense), cross-checked against StockAnalysis.com — matches.
A11: 6. Total Operating Expenses | B11: 636.6 | C11: 939.9 | D11: 1175.2 | E11: 1430.4 | F11: 1816.1 | G11: Derived per plan: Total OpEx = SG&A + R&D. Matches StockAnalysis.com reported 'Operating Expenses' line.
A12: 7. Operating Income / (Loss) | B12: -127.3 | C12: -197.3 | D12: -185.5 | E12: -139.1 | F12: -201.1 | G12: Source: StockAnalysis.com standardized income statement. May differ ~$5-15M from a given press release headline due to restructuring/impairment reclassification — see README.
A13: 8. Net Income / (Loss) | B13: -260.3 | C13: -193.4 | D13: -184 | E13: -78.8 | F13: -102.3 | G13: Source: Cloudflare Q4/FY press releases 2021–2025 (GAAP net loss attributable to common stockholders).
A14: 9. Operating Cash Flow | B14: 64.7 | C14: 123.6 | D14: 254.4 | E14: 380.4 | F14: 603.1 | G14: Source: StockAnalysis.com standardized cash flow statement, cross-checked vs. Cloudflare press releases.
A15: 10. Free Cash Flow | B15: -28.3 | C15: -20 | D15: 133.9 | E15: 180.5 | F15: 281 | G15: Source: Cloudflare Q4/FY press releases (Operating Cash Flow − CapEx), confirmed vs. StockAnalysis.com.
A16: 11. Cash, Cash Equivalents & Securities (period end) | B16: 1822 | C16: 1650 | D16: 1673.7 | E16: 1855.9 | F16: 4101 | G16: Source: Cloudflare Q4/FY press releases (period-end balance) / StockAnalysis.com balance sheet.
A18: CUSTOMER
A19: 12. Paying Customers (#, thousands) | B19: 140.1 | C19: n/a | D19: 189.8 | E19: 237.7 | F19: 332.5 | G19: Source: Cloudflare Q4 earnings call transcripts/press releases. FY2021: 140,096 (Q4'21 call, +26% YoY). FY2023: 189,791 (Q4'23, per third-party compilation of Cloudflare-reported figures). FY2024: 237,714; FY2025: ~332,466 (Q4'24/'25 press releases). FY2022 exact year-end total not found in sources reviewed (Q1'22 was 154,109) — left blank rather than guessed.
A20: 13. Large Customers (>$100K ARR, #) | B20: 1416 | C20: 2042 | D20: 2756 | E20: 3497 | F20: 4298 | G20: Source: Cloudflare Q4 2021–2025 earnings call transcripts (year-end large-customer count, each reported directly by CFO/CEO on the Q4 call).
A21: 14. $1M+ ARR Customers (#) | B21: n/a | C21: 85 | D21: 118 | E21: 173 | F21: 269 | G21: Source: Cloudflare Q4 2022/2023/2024/2025 earnings call transcripts (CFO customer-cohort commentary). FY2021 not broken out as a distinct disclosed cohort in the Q4'21 call reviewed — left blank.
A22: 15. Dollar-Based Net Retention Rate (Q4 exit rate) | B22: 1.25 | C22: 1.22 | D22: 1.15 | E22: 1.11 | F22: 1.2 | G22: Source: Cloudflare Q4 press releases/call transcripts, Q4 (year-end) exit rate. FY2022: 122% per Q4'22 earnings call transcript.
A23: 16. Large Customer Revenue Concentration (% of FY revenue) | B23: 0.54 | C23: 0.61 | D23: 0.64 | E23: 0.67 | F23: 0.69 | G23: Source: Cloudflare Q4 earnings call transcripts, full-year figure as restated each subsequent year (e.g. Q4'23 call: 'FY2023 large customers = 64% of revenue vs. 61% in 2022 and 54% in 2021').
A25: FORWARD-LOOKING
A26: 17. Remaining Performance Obligations (RPO, period end) | B26: n/a | C26: n/a | D26: n/a | E26: 1690 | F26: 2496 | G26: Source: StockAnalysis.com KPI history / Cloudflare Q4 2025 call ('$2.496 billion, up 48% YoY'). Management has referenced RPO growth rates since 2022 on calls, but a clean absolute $ figure for FY2021–23 was not found in press releases/transcripts reviewed (likely 10-K-note-only disclosure in those years) — left blank rather than estimated from a growth-rate backsolve.
A28: GEOGRAPHIC REVENUE
A29: 18. US Revenue | B29: 342.6 | C29: 515.7 | D29: 678.2 | E29: 849.5 | F29: 1073 | G29: Source: StockAnalysis.com geographic revenue breakdown (Fiscal.ai), reconciled to Cloudflare 10-K segment disclosures.
A30: 19. EMEA Revenue | B30: 172.1 | C30: 258.3 | D30: 356.6 | E30: 466.5 | F30: 598.6 | G30: Source: StockAnalysis.com geographic revenue breakdown.
A31: 20. APAC Revenue | B31: 96.5 | C31: 133.4 | D31: 168.8 | E31: 223.2 | F31: 329.8 | G31: Source: StockAnalysis.com geographic revenue breakdown.
A32: 21. Other Geographic Revenue | B32: 45.2 | C32: 67.9 | D32: 93.2 | E32: 130.4 | F32: 166.6 | G32: Source: StockAnalysis.com geographic revenue breakdown (residual region not broken out by Cloudflare).

Sheet Calculated KPIs
A1: Cloudflare, Inc. (NET) — Calculated KPIs, FY2021–FY2025
A4: KPI | B4: FY2021 | C4: FY2022 | D4: FY2023 | E4: FY2024 | F4: FY2025
A5: GROWTH & MARGINS
A6: Revenue Growth % | B6: n/a | C6: =IFERROR('Raw Data'!C6/'Raw Data'!B6-1,"n/a") -> 0.48567946 | D6: =IFERROR('Raw Data'!D6/'Raw Data'!C6-1,"n/a") -> 0.32967596 | E6: =IFERROR('Raw Data'!E6/'Raw Data'!D6-1,"n/a") -> 0.28757615 | F6: =IFERROR('Raw Data'!F6/'Raw Data'!E6-1,"n/a") -> 0.29845472
A7: Gross Margin % | B7: =IFERROR('Raw Data'!B8/'Raw Data'!B6,"n/a") -> 0.77589884 | C7: =IFERROR('Raw Data'!C8/'Raw Data'!C6,"n/a") -> 0.76148482 | D7: =IFERROR('Raw Data'!D8/'Raw Data'!D6,"n/a") -> 0.76324516 | E7: =IFERROR('Raw Data'!E8/'Raw Data'!E6,"n/a") -> 0.7731792 | F7: =IFERROR('Raw Data'!F8/'Raw Data'!F6,"n/a") -> 0.74514507
A8: Operating Margin % | B8: =IFERROR('Raw Data'!B12/'Raw Data'!B6,"n/a") -> -0.19393662 | C8: =IFERROR('Raw Data'!C12/'Raw Data'!C6,"n/a") -> -0.20231747 | D8: =IFERROR('Raw Data'!D12/'Raw Data'!D6,"n/a") -> -0.14305545 | E8: =IFERROR('Raw Data'!E12/'Raw Data'!E6,"n/a") -> -0.083313368 | F8: =IFERROR('Raw Data'!F12/'Raw Data'!F6,"n/a") -> -0.092762581
A9: Net Margin % | B9: =IFERROR('Raw Data'!B13/'Raw Data'!B6,"n/a") -> -0.39655698 | C9: =IFERROR('Raw Data'!C13/'Raw Data'!C6,"n/a") -> -0.19831829 | D9: =IFERROR('Raw Data'!D13/'Raw Data'!D6,"n/a") -> -0.14189867 | E9: =IFERROR('Raw Data'!E13/'Raw Data'!E6,"n/a") -> -0.047196933 | F9: =IFERROR('Raw Data'!F13/'Raw Data'!F6,"n/a") -> -0.047188523
A10: FCF Margin % | B10: =IFERROR('Raw Data'!B15/'Raw Data'!B6,"n/a") -> -0.043113955 | C10: =IFERROR('Raw Data'!C15/'Raw Data'!C6,"n/a") -> -0.020508614 | D10: =IFERROR('Raw Data'!D15/'Raw Data'!D6,"n/a") -> 0.10326213 | E10: =IFERROR('Raw Data'!E15/'Raw Data'!E6,"n/a") -> 0.10810973 | F10: =IFERROR('Raw Data'!F15/'Raw Data'!F6,"n/a") -> 0.12961852
A11: Cost of Revenue % of Revenue | B11: =IFERROR('Raw Data'!B7/'Raw Data'!B6,"n/a") -> 0.22410116 | C11: =IFERROR('Raw Data'!C7/'Raw Data'!C6,"n/a") -> 0.23851518 | D11: =IFERROR('Raw Data'!D7/'Raw Data'!D6,"n/a") -> 0.23675484 | E11: =IFERROR('Raw Data'!E7/'Raw Data'!E6,"n/a") -> 0.2268208 | F11: =IFERROR('Raw Data'!F7/'Raw Data'!F6,"n/a") -> 0.25485493
A12: SG&A % of Revenue (combined) | B12: =IFERROR('Raw Data'!B9/'Raw Data'!B6,"n/a") -> 0.6812919 | C12: =IFERROR('Raw Data'!C9/'Raw Data'!C6,"n/a") -> 0.65791632 | D12: =IFERROR('Raw Data'!D9/'Raw Data'!D6,"n/a") -> 0.63013804 | E12: =IFERROR('Raw Data'!E9/'Raw Data'!E6,"n/a") -> 0.60433637 | F12: =IFERROR('Raw Data'!F9/'Raw Data'!F6,"n/a") -> 0.60131925
A13: R&D % of Revenue | B13: =IFERROR('Raw Data'!B10/'Raw Data'!B6,"n/a") -> 0.28854357 | C13: =IFERROR('Raw Data'!C10/'Raw Data'!C6,"n/a") -> 0.30588597 | D13: =IFERROR('Raw Data'!D10/'Raw Data'!D6,"n/a") -> 0.27616257 | E13: =IFERROR('Raw Data'!E10/'Raw Data'!E6,"n/a") -> 0.25239578 | F13: =IFERROR('Raw Data'!F10/'Raw Data'!F6,"n/a") -> 0.23640389
A14: Total OpEx % of Revenue | B14: =IFERROR('Raw Data'!B11/'Raw Data'!B6,"n/a") -> 0.96983547 | C14: =IFERROR('Raw Data'!C11/'Raw Data'!C6,"n/a") -> 0.9638023 | D14: =IFERROR('Raw Data'!D11/'Raw Data'!D6,"n/a") -> 0.90630061 | E14: =IFERROR('Raw Data'!E11/'Raw Data'!E6,"n/a") -> 0.85673215 | F14: =IFERROR('Raw Data'!F11/'Raw Data'!F6,"n/a") -> 0.83772314
A15: Operating Cash Flow Growth % | B15: n/a | C15: =IFERROR('Raw Data'!C14/'Raw Data'!B14-1,"n/a") -> 0.91035549 | D15: =IFERROR('Raw Data'!D14/'Raw Data'!C14-1,"n/a") -> 1.0582524 | E15: =IFERROR('Raw Data'!E14/'Raw Data'!D14-1,"n/a") -> 0.49528302 | F15: =IFERROR('Raw Data'!F14/'Raw Data'!E14-1,"n/a") -> 0.58543638
A16: FCF Growth % | B16: n/a | C16: =IFERROR('Raw Data'!C15/'Raw Data'!B15-1,"n/a") -> -0.29328622 | D16: =IFERROR('Raw Data'!D15/'Raw Data'!C15-1,"n/a") -> -7.695 | E16: =IFERROR('Raw Data'!E15/'Raw Data'!D15-1,"n/a") -> 0.34802091 | F16: =IFERROR('Raw Data'!F15/'Raw Data'!E15-1,"n/a") -> 0.5567867
A17: Cash & Securities Growth % | B17: n/a | C17: =IFERROR('Raw Data'!C16/'Raw Data'!B16-1,"n/a") -> -0.094401756 | D17: =IFERROR('Raw Data'!D16/'Raw Data'!C16-1,"n/a") -> 0.014363636 | E17: =IFERROR('Raw Data'!E16/'Raw Data'!D16-1,"n/a") -> 0.10886061 | F17: =IFERROR('Raw Data'!F16/'Raw Data'!E16-1,"n/a") -> 1.2097096
A19: CUSTOMER
A20: Paying Customer Growth % | B20: n/a | C20: =IFERROR('Raw Data'!C19/'Raw Data'!B19-1,"n/a") -> n/a | D20: =IFERROR('Raw Data'!D19/'Raw Data'!C19-1,"n/a") -> n/a | E20: =IFERROR('Raw Data'!E19/'Raw Data'!D19-1,"n/a") -> 0.25237092 | F20: =IFERROR('Raw Data'!F19/'Raw Data'!E19-1,"n/a") -> 0.39882204
A21: Large Customer Growth % | B21: n/a | C21: =IFERROR('Raw Data'!C20/'Raw Data'!B20-1,"n/a") -> 0.4420904 | D21: =IFERROR('Raw Data'!D20/'Raw Data'!C20-1,"n/a") -> 0.3496572 | E21: =IFERROR('Raw Data'!E20/'Raw Data'!D20-1,"n/a") -> 0.26886792 | F21: =IFERROR('Raw Data'!F20/'Raw Data'!E20-1,"n/a") -> 0.22905347
A22: $1M+ Customer Growth % | B22: n/a | C22: =IFERROR('Raw Data'!C21/'Raw Data'!B21-1,"n/a") -> n/a | D22: =IFERROR('Raw Data'!D21/'Raw Data'!C21-1,"n/a") -> 0.38823529 | E22: =IFERROR('Raw Data'!E21/'Raw Data'!D21-1,"n/a") -> 0.46610169 | F22: =IFERROR('Raw Data'!F21/'Raw Data'!E21-1,"n/a") -> 0.55491329
A23: Revenue per Paying Customer ($, thousands) | B23: =IFERROR('Raw Data'!B6/'Raw Data'!B19,"n/a") -> 4.6852248 | C23: =IFERROR('Raw Data'!C6/'Raw Data'!C19,"n/a") -> n/a | D23: =IFERROR('Raw Data'!D6/'Raw Data'!D19,"n/a") -> 6.8319283 | E23: =IFERROR('Raw Data'!E6/'Raw Data'!E19,"n/a") -> 7.0239798 | F23: =IFERROR('Raw Data'!F6/'Raw Data'!F19,"n/a") -> 6.52
A24: Large Customer Revenue Concentration % (linked) | B24: =IFERROR('Raw Data'!B23,"n/a") -> 0.54 | C24: =IFERROR('Raw Data'!C23,"n/a") -> 0.61 | D24: =IFERROR('Raw Data'!D23,"n/a") -> 0.64 | E24: =IFERROR('Raw Data'!E23,"n/a") -> 0.67 | F24: =IFERROR('Raw Data'!F23,"n/a") -> 0.69
A25: Dollar-Based Net Retention Rate (linked) | B25: =IFERROR('Raw Data'!B22,"n/a") -> 1.25 | C25: =IFERROR('Raw Data'!C22,"n/a") -> 1.22 | D25: =IFERROR('Raw Data'!D22,"n/a") -> 1.15 | E25: =IFERROR('Raw Data'!E22,"n/a") -> 1.11 | F25: =IFERROR('Raw Data'!F22,"n/a") -> 1.2
A27: FORWARD-LOOKING
A28: RPO Growth % | B28: n/a | C28: =IFERROR('Raw Data'!C26/'Raw Data'!B26-1,"n/a") -> n/a | D28: =IFERROR('Raw Data'!D26/'Raw Data'!C26-1,"n/a") -> n/a | E28: =IFERROR('Raw Data'!E26/'Raw Data'!D26-1,"n/a") -> n/a | F28: =IFERROR('Raw Data'!F26/'Raw Data'!E26-1,"n/a") -> 0.47692308
A29: Revenue + RPO Combined Growth % | B29: n/a | C29: =IFERROR((('Raw Data'!C6+'Raw Data'!C26)/('Raw Data'!B6+'Raw Data'!B26))-1,"n/a") -> n/a | D29: =IFERROR((('Raw Data'!D6+'Raw Data'!D26)/('Raw Data'!C6+'Raw Data'!C26))-1,"n/a") -> n/a | E29: =IFERROR((('Raw Data'!E6+'Raw Data'!E26)/('Raw Data'!D6+'Raw Data'!D26))-1,"n/a") -> n/a | F29: =IFERROR((('Raw Data'!F6+'Raw Data'!F26)/('Raw Data'!E6+'Raw Data'!E26))-1,"n/a") -> 0.38823074
A31: GEOGRAPHIC MIX (% of total revenue)
A32: US % of Revenue | B32: =IFERROR('Raw Data'!B29/'Raw Data'!B6,"n/a") -> 0.52193784 | C32: =IFERROR('Raw Data'!C29/'Raw Data'!C6,"n/a") -> 0.5288146 | D32: =IFERROR('Raw Data'!D29/'Raw Data'!D6,"n/a") -> 0.52301997 | E32: =IFERROR('Raw Data'!E29/'Raw Data'!E6,"n/a") -> 0.5088045 | F32: =IFERROR('Raw Data'!F29/'Raw Data'!F6,"n/a") -> 0.49494903
A33: EMEA % of Revenue | B33: =IFERROR('Raw Data'!B30/'Raw Data'!B6,"n/a") -> 0.26218769 | C33: =IFERROR('Raw Data'!C30/'Raw Data'!C6,"n/a") -> 0.26486874 | D33: =IFERROR('Raw Data'!D30/'Raw Data'!D6,"n/a") -> 0.27500578 | E33: =IFERROR('Raw Data'!E30/'Raw Data'!E6,"n/a") -> 0.27940824 | F33: =IFERROR('Raw Data'!F30/'Raw Data'!F6,"n/a") -> 0.27611975
A34: APAC % of Revenue | B34: =IFERROR('Raw Data'!B31/'Raw Data'!B6,"n/a") -> 0.14701402 | C34: =IFERROR('Raw Data'!C31/'Raw Data'!C6,"n/a") -> 0.13679245 | D34: =IFERROR('Raw Data'!D31/'Raw Data'!D6,"n/a") -> 0.1301766 | E34: =IFERROR('Raw Data'!E31/'Raw Data'!E6,"n/a") -> 0.13368471 | F34: =IFERROR('Raw Data'!F31/'Raw Data'!F6,"n/a") -> 0.15212879
A35: Other Geographic % of Revenue | B35: =IFERROR('Raw Data'!B32/'Raw Data'!B6,"n/a") -> 0.068860451 | C35: =IFERROR('Raw Data'!C32/'Raw Data'!C6,"n/a") -> 0.069626743 | D35: =IFERROR('Raw Data'!D32/'Raw Data'!D6,"n/a") -> 0.071874759 | E35: =IFERROR('Raw Data'!E32/'Raw Data'!E6,"n/a") -> 0.07810254 | F35: =IFERROR('Raw Data'!F32/'Raw Data'!F6,"n/a") -> 0.076848563
A38: 4-YEAR CAGR (FY2021 → FY2025)
A39: Revenue CAGR | B39: =IFERROR(('Raw Data'!F6/'Raw Data'!B6)^(1/4)-1,"n/a") -> 0.34808622
A40: Customer CAGR (FY2023–FY2025, 2-yr — earlier years n/a) | B40: =IFERROR(('Raw Data'!F19/'Raw Data'!D19)^(1/2)-1,"n/a") -> 0.32357246
A41: FCF CAGR (FY2023–FY2025, 2-yr — FY21/22 FCF negative, CAGR not meaningful) | B41: =IFERROR(('Raw Data'!F15/'Raw Data'!D15)^(1/2)-1,"n/a") -> 0.448648
